Metadata-Version: 2.1
Name: uncleflashcard
Version: 0.1
Summary: Uncle Flashcard by Uncle Engineer
Home-page: https://github.com/UncleEngineer/uncleflashcard
Download-URL: https://github.com/UncleEngineer/uncleflashcard/archive/v_01.tar.gz
Author: Loong Wissawakorn
Author-email: loong.wissawakorn@gmail.com
License: MIT
Keywords: Flashcard,Memorise,Uncle Engineer
Classifier: Development Status :: 3 - Alpha
Classifier: Intended Audience :: Developers
Classifier: Topic :: Software Development :: Build Tools
Classifier: License :: OSI Approved :: MIT License
Classifier: Programming Language :: Python :: 3
Classifier: Programming Language :: Python :: 3.4
Classifier: Programming Language :: Python :: 3.5
Classifier: Programming Language :: Python :: 3.6
Classifier: Programming Language :: Python :: 3.7
Classifier: Programming Language :: Python :: 3.8
Classifier: Programming Language :: Python :: 3.9
Classifier: Programming Language :: Python :: 3.10
Classifier: Programming Language :: Python :: 3.11
Classifier: Programming Language :: Python :: 3.12
License-File: LICENSE
License-File: LICENSE.txt
